README.md
setup.cfg
setup.py
moneyforward_acplus/__init__.py
moneyforward_acplus/api_client.py
moneyforward_acplus/configuration.py
moneyforward_acplus/exceptions.py
moneyforward_acplus/rest.py
moneyforward_acplus.egg-info/PKG-INFO
moneyforward_acplus.egg-info/SOURCES.txt
moneyforward_acplus.egg-info/dependency_links.txt
moneyforward_acplus.egg-info/requires.txt
moneyforward_acplus.egg-info/top_level.txt
moneyforward_acplus/api/__init__.py
moneyforward_acplus/api/accounts_api.py
moneyforward_acplus/api/journals_api.py
moneyforward_acplus/api/sub_accounts_api.py
moneyforward_acplus/models/__init__.py
moneyforward_acplus/models/account.py
moneyforward_acplus/models/create_journal_file_request.py
moneyforward_acplus/models/create_journal_file_response.py
moneyforward_acplus/models/error.py
moneyforward_acplus/models/error_detail.py
moneyforward_acplus/models/journal_file_status.py
moneyforward_acplus/models/sub_account.py
test/test_account.py
test/test_accounts_api.py
test/test_create_journal_file_request.py
test/test_create_journal_file_response.py
test/test_error.py
test/test_error_detail.py
test/test_journal_file_status.py
test/test_journals_api.py
test/test_sub_account.py
test/test_sub_accounts_api.py